{
  "name": "Example Scanner",
  "description": "An example module that demonstrates how to create a scanner for BSTG",
  "version": "1.0.0",
  "author": "Your Name",
  "type": "bash",
  "args": [
    {
      "name": "target_host",
      "description": "Target host to scan",
      "type": "string",
      "required": true
    },
    {
      "name": "port",
      "description": "Port to scan",
      "type": "int",
      "required": true,
      "default": "443"
    },
    {
      "name": "scan_type",
      "description": "Type of scan to perform (quick or full)",
      "type": "string",
      "required": false,
      "default": "quick"
    }
  ],
  "tags": ["scanner", "example", "network"]
}
